myfunctions_namazsari/__init__.py
myfunctions_namazsari/math.py
myfunctions_namazsari-0.0.8.dist-info/METADATA
myfunctions_namazsari-0.0.8.dist-info/WHEEL
myfunctions_namazsari-0.0.8.dist-info/top_level.txt
myfunctions_namazsari-0.0.8.dist-info/RECORD
